data_go_mcp/nts_business_verification/__init__.py
data_go_mcp/nts_business_verification/api_client.py
data_go_mcp/nts_business_verification/models.py
data_go_mcp/nts_business_verification/server.py
data_go_mcp_nts_business_verification-0.2.0.dist-info/METADATA
data_go_mcp_nts_business_verification-0.2.0.dist-info/WHEEL
data_go_mcp_nts_business_verification-0.2.0.dist-info/entry_points.txt
data_go_mcp_nts_business_verification-0.2.0.dist-info/licenses/LICENSE
data_go_mcp_nts_business_verification-0.2.0.dist-info/RECORD
