Metadata-Version: 2.4
Name: data-go-mcp.nts-business-verification
Version: 0.2.0
Summary: MCP server for 국세청 사업자등록정보 진위확인 및 상태조회 서비스
Project-URL: Homepage, https://github.com/Koomook/data-go-mcp-servers
Project-URL: Repository, https://github.com/Koomook/data-go-mcp-servers
Project-URL: Documentation, https://github.com/Koomook/data-go-mcp-servers/tree/main/src/nts-business-verification
Project-URL: Bug Tracker, https://github.com/Koomook/data-go-mcp-servers/issues
Project-URL: Changelog, https://github.com/Koomook/data-go-mcp-servers/blob/main/src/nts-business-verification/CHANGELOG.md
Author-email: Your Name <your.email@example.com>
License: Apache-2.0
License-File: LICENSE
Keywords: api,data.go.kr,korea,mcp,nts-business-verification
Classifier: Development Status :: 3 - Alpha
Classifier: Intended Audience :: Developers
Classifier: License :: OSI Approved :: Apache Software License
Classifier: Programming Language :: Python :: 3
Classifier: Programming Language :: Python :: 3.10
Classifier: Programming Language :: Python :: 3.11
Classifier: Programming Language :: Python :: 3.12
Classifier: Programming Language :: Python :: 3.13
Requires-Python: >=3.10
Requires-Dist: httpx>=0.28.1
Requires-Dist: mcp[cli]>=1.13.0
Requires-Dist: pydantic>=2.11.7
Requires-Dist: python-dotenv>=1.1.1
